tradepose_client/__init__.py
tradepose_client/client.py
tradepose_client/config.py
tradepose_client/exceptions.py
tradepose_client/types.py
tradepose_client/utils.py
tradepose_client/analysis/__init__.py
tradepose_client/analysis/mae_mfe/SPEC.md
tradepose_client/analysis/mae_mfe/__init__.py
tradepose_client/analysis/mae_mfe/analyzer.py
tradepose_client/analysis/mae_mfe/charts.py
tradepose_client/analysis/mae_mfe/config.py
tradepose_client/analysis/mae_mfe/rolling.py
tradepose_client/analysis/mae_mfe/statistics.py
tradepose_client/analysis/mae_mfe/types.py
tradepose_client/auth/__init__.py
tradepose_client/auth/api_key.py
tradepose_client/auth/jwt.py
tradepose_client/batch/README.md
tradepose_client/batch/__init__.py
tradepose_client/batch/background.py
tradepose_client/batch/cache.py
tradepose_client/batch/models.py
tradepose_client/batch/results.py
tradepose_client/batch/tester.py
tradepose_client/builder/__init__.py
tradepose_client/builder/blueprint_builder.py
tradepose_client/builder/strategy_builder.py
tradepose_client/builder/trading_context.py
tradepose_client/portfolio/__init__.py
tradepose_client/portfolio/portfolio_builder.py
tradepose_client/registry/__init__.py
tradepose_client/registry/strategy_registry.py
tradepose_client/resources/__init__.py
tradepose_client/resources/accounts.py
tradepose_client/resources/api_keys.py
tradepose_client/resources/base.py
tradepose_client/resources/billing.py
tradepose_client/resources/bindings.py
tradepose_client/resources/export.py
tradepose_client/resources/instruments.py
tradepose_client/resources/portfolios.py
tradepose_client/resources/slots.py
tradepose_client/resources/strategies.py
tradepose_client/resources/tasks.py
tradepose_client/resources/trades.py
tradepose_client/resources/usage.py
tradepose_client/setup/__init__.py
tradepose_client/setup/trading_setup.py
tradepose_client-1.5.0.dist-info/METADATA
tradepose_client-1.5.0.dist-info/WHEEL
tradepose_client-1.5.0.dist-info/RECORD
