Metadata-Version: 2.4
Name: tradepose-client
Version: 1.5.0
Summary: Python client SDK for TradePose trading platform
Author-email: TradePose Team <codeotter0201@gmail.com>
License: MIT
Keywords: client,quantitative,sdk,trading
Classifier: Development Status :: 3 - Alpha
Classifier: Intended Audience :: Developers
Classifier: Intended Audience :: Financial and Insurance Industry
Classifier: License :: OSI Approved :: MIT License
Classifier: Operating System :: OS Independent
Classifier: Programming Language :: Python :: 3
Classifier: Programming Language :: Python :: 3.13
Classifier: Topic :: Office/Business :: Financial :: Investment
Classifier: Topic :: Software Development :: Libraries :: Python Modules
Requires-Python: >=3.13
Requires-Dist: httpx[http2]>=0.28.1
Requires-Dist: nest-asyncio>=1.6.0
Requires-Dist: polars
Requires-Dist: pyarrow
Requires-Dist: pydantic-settings>=2.7.0
Requires-Dist: pydantic>=2.12.1
Requires-Dist: tradepose-models>=1.4.0
Provides-Extra: analysis
Requires-Dist: kaleido>=0.2.1; extra == 'analysis'
Requires-Dist: plotly>=6.0.0; extra == 'analysis'
Requires-Dist: scipy>=1.14.0; extra == 'analysis'
Provides-Extra: dev
Requires-Dist: mypy>=1.13.0; extra == 'dev'
Requires-Dist: pytest-asyncio>=0.24.0; extra == 'dev'
Requires-Dist: pytest-mock>=3.14.0; extra == 'dev'
Requires-Dist: pytest>=8.0.0; extra == 'dev'
Requires-Dist: respx>=0.21.0; extra == 'dev'
Requires-Dist: ruff>=0.8.0; extra == 'dev'
Provides-Extra: optional
Requires-Dist: orjson>=3.10.0; extra == 'optional'
Requires-Dist: rich>=13.0.0; extra == 'optional'
Requires-Dist: tenacity>=9.0.0; extra == 'optional'
